Week 2/ALU/source/alu.v
module alu #(parameter BIT_LENGTH = 4)(
    input [BIT_LENGTH-1:0] a, 
    input [BIT_LENGTH-1:0] b, 
    input [2:0] opcode, 
    input funct, 
    input exec_en, 
    output reg [BIT_LENGTH-1:0] out,
    output reg cb
);
    
    wire [3:0] operator; 
    assign operator = {funct, opcode}; 
    always @(*) begin
        //$display("[%0t] Operator %b",$time, operator); 
        if (exec_en) begin
            case(operator)
                4'b0000: {cb, out} = a + b; 
                4'b1000: {cb, out} = a - b; 
                4'b0001: {cb, out} = a & b; 
                4'b0010: {cb, out} = a | b; 
                4'b0011: {cb, out} = ~a; 
                4'b1100: {cb, out} = ~b; 
                4'b0101: begin
                    {cb, out} = a ^ b; 
                    //$display("[%0t] Inside XOR %b",$time, {cb, out}   );
                end
                4'b1101: {cb, out} = ~(a ^ b); 
                4'b1001: {cb, out} = ~(a & b); 
                4'b1010: {cb, out} = ~(a | b); 
                4'b0110: {cb, out} = a << b; 
                4'b0111: {cb, out} = a >> b; 
                default: {cb, out} = 'bx; 
            endcase
        end
        else 
            {cb, out} = 'b0; 
    end

endmodule

Week_2/ALU/source/controller.v
module controller(
    input clk, 
    input reset_n, 
    input start, 
    
    output reg exec_en, 
    output reg rvalid
); 

    reg [1:0] present_state, next_state; 

    parameter IDLE = 2'b00; 
    parameter LOAD = 2'b01; 
    parameter EXECUTE = 2'b10; 
    parameter MEM_WRITE = 2'b11; 


    always @(*) begin
        begin: NSL
            case(present_state)
                IDLE: next_state = start? LOAD: IDLE; 
                LOAD: next_state = EXECUTE; 
                EXECUTE: next_state = MEM_WRITE;
                MEM_WRITE: next_state = IDLE;  
                default: next_state = 'bx; 
        endcase
        end 

        begin: OL
            case(present_state)
                IDLE: begin
                    rvalid = 0; 
                    exec_en = 0; 
                end
                LOAD: begin
                    rvalid = 0; 
                    exec_en = 0; 
                end 
                EXECUTE: begin
                    rvalid = 0; 
                    exec_en = 1; 
                end 
                MEM_WRITE: begin
                    rvalid = 1; 
                    exec_en = 0; 
                end 


            endcase
    end 

    end 

    always @(posedge clk or negedge reset_n) begin
        if(!reset_n)
            present_state <= IDLE; 
        else 
            present_state <= next_state; 
        
    end

endmodule

Week_2/ALU/source/top.v
`include "./source/alu.v"
`include "./source/shift_reg.v"
`include "./source/controller.v"

module top #(parameter INSTR_LENGTH = 12)(
    input clk, 
    input reset_n, 
    input start, 
    input [INSTR_LENGTH-1:0] instruction, 

    output [3:0] result,
    output cb,
    output rvalid
); 

    wire [INSTR_LENGTH-1:0] data_out;
    wire in_cb; 
    wire [3:0] in_result; 
    wire rvalid;  
    wire [4:0] result_out;


    controller CONTROL(
        .clk(clk), 
        .reset_n(reset_n), 
        .start(start), 
        .exec_en(exec_en), 
        .rvalid(rvalid)
    ); 

    alu ALU(
        .a(instruction[10:7]), 
        .b(instruction[6:3]), 
        .opcode(instruction[2:0]), 
        .funct(instruction[11]),
        .exec_en(exec_en),
        .out(result),
        .cb(cb)
    ); 

    assign result = result_out[3:0]; 
    assign cb = result_out[4];

endmodule

Week 2/ALU/test/top_tb.sv
`include "./source/top.v"

module top_tb; 
    reg clk = 0; 
    logic reset_n = 1; 
    logic start = 0; 
    logic [11:0] instruction; 

    wire [3:0] result;
    wire cb, rvalid; 

  	logic [3:0] a = 4'b1011; 
  	logic [3:0] b = 4'b1010; 
 	logic [2:0] opcode = 3'b010; 
    logic funct = 1; 

    logic [3:0] expected_result; 
    reg [15:0] operation; 


    initial begin
      	clk = 0; 
        forever begin
            #1; 
            clk = ~clk; 
        end
    end

    initial begin
        a = $random; 
        b = $random; 
        instruction = {funct, a, b, opcode};
        @(negedge clk)
        reset_n = 0; 
        @(negedge clk)
      	reset_n = 1; 
      	@(negedge clk)
        start = 1; 
      
        opcode = 3'b000; 
        funct = 0;
        instruction = {funct, a, b, opcode};
        expected_result = a + b;
        operation = "+";
        @(posedge rvalid);
        //if(result != expected_result) 
            $display("[%0t] %b %s %b = %b >>>>> Got = %b", $time, a, operation, b, expected_result, result);

        opcode = 3'b000; 
        funct = 1; 
        instruction = {funct, a, b, opcode};
        expected_result = a - b;
        operation = "-";
        @(posedge rvalid);
        //if(result != expected_result) 
            $display("[%0t] %b %s %b = %b >>>>> Got = %b", $time, a, operation, b, expected_result, result);

       opcode = 3'b001; 
        funct = 0; 
        instruction = {funct, a, b, opcode};
        expected_result = a & b;
        operation = "&";
        @(posedge rvalid);
        //if(result != expected_result) 
            $display("[%0t] %b %s %b = %b >>>>> Got = %b", $time, a, operation, b, expected_result, result);

        opcode = 3'b001; 
        funct = 1; 
        instruction = {funct, a, b, opcode};
        expected_result = ~(a & b);
        operation = "~&";
        @(posedge rvalid);
        //if(result != expected_result) 
            $display("[%0t] %b %s %b = %b >>>>> Got = %b", $time, a, operation, b, expected_result, result);

        opcode = 3'b010; 
        funct = 0; 
        instruction = {funct, a, b, opcode};
        expected_result = a | b;
        operation = "|";
        @(posedge rvalid);
        //if(result != expected_result) 
            $display("[%0t] %b %s %b = %b >>>>> Got = %b", $time, a, operation, b, expected_result, result);

        opcode = 3'b010; 
        funct = 1; 
        instruction = {funct, a, b, opcode};
        expected_result = a ~| b;
        operation = "~|";
        @(posedge rvalid);
        //if(result != expected_result) 
            $display("[%0t] %b %s %b = %b >>>>> Got = %b", $time, a, operation, b, expected_result, result);


        opcode = 3'b011; 
        funct = 0; 
        instruction = {funct, a, b, opcode};
        expected_result = ~a;
        operation = "~";
        @(posedge rvalid);
        //if(result != expected_result) 
            $display("[%0t] a %s %b = %b >>>>> Got = %b", $time, operation, a, expected_result, result);


        opcode = 3'b100; 
        funct = 1; 
        instruction = {funct, a, b, opcode};
        expected_result = ~ b;
        operation = "~";
        @(posedge rvalid); 
        //if(result != expected_result) 
            $display("[%0t] %s %b = %b >>>>> Got = %b", $time, operation, b, expected_result, result);
 
        opcode = 3'b101; 
        funct = 0; 
        instruction = {funct, a, b, opcode};
        expected_result = a ^ b;
        operation = "^";
        @(posedge rvalid); 
        //if(result != expected_result) 
            $display("[%0t] %b %s %b = %b >>>>> Got = %b", $time, a, operation, b, expected_result, result);

        opcode = 3'b101; 
        funct = 1; 
        instruction = {funct, a, b, opcode};
        expected_result = a ~^ b;
        operation = "~^";
        @(posedge rvalid);
        if(result != expected_result) 
            $display("[%0t] %b %s %b = %b >>>>> Got = %b", $time, a, operation, b, expected_result, result);

        opcode = 3'b110; 
        funct = 0; 
        b = 4'b010; 
        instruction = {funct, a, b, opcode};
        expected_result = a << b; 
        operation = "<<"; 
        @(posedge rvalid); 
        //if(result != expected_result) 
            $display("[%0t] %b %s %b = %b >>>>> Got = %b", $time, a, operation, b, expected_result, result);
        //end
        #10 
        $finish; 

    end 

    initial begin
        $dumpfile("./waveform/top_tb.vcd");
        $dumpvars; 
    end 
  
  	top DUT(
        .clk(clk), 
        .reset_n(reset_n), 
        .start(start), 
        .instruction(instruction), 
        .result(result), 
      	.cb(cb), 
        .rvalid(rvalid)
    ); 

endmodule

Week 2/ALU/source/shift_reg.v
module shift_reg #(parameter DATA_LENGTH = 12)(
    input clk, 
    input reset_n, 
    input shift_en, 
    input [DATA_LENGTH-1:0] data_in_p,
    output reg [DATA_LENGTH-1:0] data_out_p
); 

    always @(posedge clk or negedge reset_n) begin
        if(!reset_n)
            data_out_p <= 'b0; 
        else 
            data_out_p <= shift_en ? data_in_p: data_out_p; 
    end 
endmodule

Week 2/ALU/waveform/top_tb.vcd
$date
	Fri Jan 06 23:19:28 2023
$end
$version
	Icarus Verilog
$end
$timescale
	1s
$end
$scope module shift_reg $end
$var wire 1 ! clk $end
$var wire 12 " data_in_p [11:0] $end
$var wire 1 # reset_n $end
$var wire 1 $ shift_en $end
$var parameter 32 % DATA_LENGTH $end
$var reg 12 & data_out_p [11:0] $end
$upscope $end
$scope module top_tb $end
$var wire 1 ' cb $end
$var wire 4 ( result [3:0] $end
$var wire 1 ) rvalid $end
$var reg 4 * a [3:0] $end
$var reg 4 + b [3:0] $end
$var reg 1 , clk $end
$var reg 4 - expected_result [3:0] $end
$var reg 1 . funct $end
$var reg 12 / instruction [11:0] $end
$var reg 3 0 opcode [2:0] $end
$var reg 16 1 operation [15:0] $end
$var reg 1 2 reset_n $end
$var reg 1 3 start $end
$scope module DUT $end
$var wire 1 ' cb $end
$var wire 1 , clk $end
$var wire 12 4 instruction [11:0] $end
$var wire 1 2 reset_n $end
$var wire 4 5 result [3:0] $end
$var wire 5 6 result_out [4:0] $end
$var wire 1 3 start $end
$var wire 1 ) rvalid $end
$var wire 1 7 exec_en $end
$var parameter 32 8 INSTR_LENGTH $end
$scope module ALU $end
$var wire 4 9 a [3:0] $end
$var wire 4 : b [3:0] $end
$var wire 1 ; funct $end
$var wire 3 < opcode [2:0] $end
$var wire 4 = operator [3:0] $end
$var wire 1 7 exec_en $end
$var parameter 32 > BIT_LENGTH $end
$var reg 1 ? cb $end
$var reg 4 @ out [3:0] $end
$upscope $end
$scope module CONTROL $end
$var wire 1 , clk $end
$var wire 1 2 reset_n $end
$var wire 1 3 start $end
$var parameter 2 A EXECUTE $end
$var parameter 2 B IDLE $end
$var parameter 2 C LOAD $end
$var parameter 2 D MEM_WRITE $end
$var reg 1 7 exec_en $end
$var reg 2 E next_state [1:0] $end
$var reg 2 F present_state [1:0] $end
$var reg 1 ) rvalid $end
$scope begin NSL $end
$upscope $end
$scope begin OL $end
$upscope $end
$upscope $end
$upscope $end
$upscope $end
$enddefinitions $end
$comment Show the parameter values. $end
$dumpall
b11 D
b1 C
b0 B
b10 A
b100 >
b1100 8
b1100 %
$end
#0
$dumpvars
bx F
bx E
b0 @
0?
b1010 =
b10 <
1;
b1 :
b100 9
x7
bz 6
b0 5
b101000001010 4
03
12
bx 1
b10 0
b101000001010 /
1.
bx -
0,
b1 +
b100 *
x)
b0 (
0'
bx &
z$
z#
bz "
z!
$end
#1
1,
#2
07
0)
b0 E
b0 F
02
0,
#3
1,
#4
12
0,
#5
1,
#6
b0 <
b0 =
0;
b1 E
b101011 1
b101 -
b1000001000 /
b1000001000 4
0.
b0 0
13
0,
#7
b10 E
b1 F
1,
#8
0,
#9
b101 (
b101 5
b101 @
17
b11 E
b10 F
1,
#10
0,
#11
b1000 =
1;
b0 (
b0 5
b0 @
b101101 1
b11 -
b101000001000 /
b101000001000 4
1.
07
1)
b0 E
b11 F
1,
#12
0,
#13
0)
b1 E
b0 F
1,
#14
0,
#15
b10 E
b1 F
1,
#16
0,
#17
b11 (
b11 5
b11 @
17
b11 E
b10 F
1,
#18
0,
#19
b1 <
b1 =
0;
b0 (
b0 5
b0 @
b100110 1
b0 -
b1000001001 /
b1000001001 4
0.
b1 0
07
1)
b0 E
b11 F
1,
#20
0,
#21
0)
b1 E
b0 F
1,
#22
0,
#23
b10 E
b1 F
1,
#24
0,
#25
17
b11 E
b10 F
1,
#26
0,
#27
b1001 =
1;
b111111000100110 1
b1111 -
b101000001001 /
b101000001001 4
1.
07
1)
b0 E
b11 F
1,
#28
0,
#29
0)
b1 E
b0 F
1,
#30
0,
#31
b10 E
b1 F
1,
#32
0,
#33
1'
1?
b1111 (
b1111 5
b1111 @
17
b11 E
b10 F
1,
#34
0,
#35
b10 <
b10 =
0;
0'
0?
b0 (
b0 5
b0 @
b1111100 1
b101 -
b1000001010 /
b1000001010 4
0.
b10 0
07
1)
b0 E
b11 F
1,
#36
0,
#37
0)
b1 E
b0 F
1,
#38
0,
#39
b10 E
b1 F
1,
#40
0,
#41
b101 (
b101 5
b101 @
17
b11 E
b10 F
1,
#42
0,
#43
b1010 =
1;
b0 (
b0 5
b0 @
b111111001111100 1
b1010 -
b101000001010 /
b101000001010 4
1.
07
1)
b0 E
b11 F
1,
#44
0,
#45
0)
b1 E
b0 F
1,
#46
0,
#47
b10 E
b1 F
1,
#48
0,
#49
1'
1?
b1010 (
b1010 5
b1010 @
17
b11 E
b10 F
1,
#50
0,
#51
b11 <
b11 =
0;
0'
0?
b0 (
b0 5
b0 @
b1111110 1
b1011 -
b1000001011 /
b1000001011 4
0.
b11 0
07
1)
b0 E
b11 F
1,
#52
0,
#53
0)
b1 E
b0 F
1,
#54
0,
#55
b10 E
b1 F
1,
#56
0,
#57
1'
1?
b1011 (
b1011 5
b1011 @
17
b11 E
b10 F
1,
#58
0,
#59
b100 <
b1100 =
1;
0'
0?
b0 (
b0 5
b0 @
b1110 -
b101000001100 /
b101000001100 4
1.
b100 0
07
1)
b0 E
b11 F
1,
#60
0,
#61
0)
b1 E
b0 F
1,
#62
0,
#63
b10 E
b1 F
1,
#64
0,
#65
1'
1?
b1110 (
b1110 5
b1110 @
17
b11 E
b10 F
1,
#66
0,
#67
b101 <
b101 =
0;
0'
0?
b0 (
b0 5
b0 @
b1011110 1
b101 -
b1000001101 /
b1000001101 4
0.
b101 0
07
1)
b0 E
b11 F
1,
#68
0,
#69
0)
b1 E
b0 F
1,
#70
0,
#71
b10 E
b1 F
1,
#72
0,
#73
b101 (
b101 5
b101 @
17
b11 E
b10 F
1,
#74
0,
#75
b1101 =
1;
b0 (
b0 5
b0 @
b111111001011110 1
b1010 -
b101000001101 /
b101000001101 4
1.
07
1)
b0 E
b11 F
1,
#76
0,
#77
0)
b1 E
b0 F
1,
#78
0,
#79
b10 E
b1 F
1,
#80
0,
#81
1'
1?
b1010 (
b1010 5
b1010 @
17
b11 E
b10 F
1,
#82
0,
#83
b10 :
b110 <
b110 =
0;
0'
0?
b0 (
b0 5
b0 @
b11110000111100 1
b0 -
b1000010110 /
b1000010110 4
b10 +
0.
b110 0
07
1)
b0 E
b11 F
1,
#84
0,
#85
0)
b1 E
b0 F
1,
#86
0,
#87
b10 E
b1 F
1,
#88
0,
#89
1'
1?
17
b11 E
b10 F
1,
#90
0,
#91
0'
0?
07
1)
b0 E
b11 F
1,
#92
0,
#93
0)
b1 E
b0 F
1,
#94
0,
#95
b10 E
b1 F
1,
#96
0,
#97
1'
1?
17
b11 E
b10 F
1,
#98
0,
#99
0'
0?
07
1)
b0 E
b11 F
1,
#100
0,
#101
0)
b1 E
b0 F
1,
