Week_2/FSM/source/shift_register.v
module shift_register #(parameter DATA_WIDTH = 5) (
    input clk, 
    input reset_n, 
    input shift_en, 
    input data_in, 
    output reg [DATA_WIDTH - 1: 0] data_out
); 

    always @(posedge clk or negedge reset_n) begin
        if (!reset_n) begin 
            data_out <= 'b0; 
        end 
        else begin
            data_out <= shift_en ? {data_in, data_out[DATA_WIDTH - 1: 1]} : data_out; 
        end 
    end 
endmodule

Week_2/FSM/source/shift_register_tb.sv
`include "shift_register.v"
module shift_register_tb; 
    reg clk, reset_n, shift_en, data_in; 
    wire [4:0] data_out; 

    integer i;

    initial begin
        clk = 0; 
        reset_n = 1; 
        shift_en = 0; 
        data_in = 'bx; 
        
        forever begin
            clk = ~clk; 
            #1;
        end 
    end 

    initial begin 
        @(posedge clk); 
        reset_n = 0; 
        @(posedge clk); 
        shift_en = 0;
        reset_n = 1;  

        i = 0; 
        repeat(100) begin
            data_in = $random; 
            if (i == 4) begin
                shift_en = 1; 
                i = 0; 
            end 
            else shift_en = 0; 
            i = i + 1; 
            @(posedge clk); 
        end 

        #10
        $finish; 
    end 


    initial begin
        $dumpfile("shift.vcd"); 
        $dumpvars; 
    end 

    shift_register REG(
        .clk(clk), 
        .reset_n(reset_n), 
        .shift_en(shift_en), 
        .data_in(data_in), 
        .data_out(data_out)
    ); 

    endmodule

Week_2/FSM/shift.vcd
$date
	Sat Jan 07 01:54:04 2023
$end
$version
	ModelSim Version 2020.1
$end
$timescale
	1ns
$end

$scope module shift_register_tb $end
$var reg 1 ! clk $end
$var reg 1 " reset_n $end
$var reg 1 # shift_en $end
$var reg 1 $ data_in $end
$var wire 1 % data_out [4] $end
$var wire 1 & data_out [3] $end
$var wire 1 ' data_out [2] $end
$var wire 1 ( data_out [1] $end
$var wire 1 ) data_out [0] $end
$var integer 32 * i $end

$scope module REG $end
$var parameter 32 + DATA_WIDTH $end
$var wire 1 , clk $end
$var wire 1 - reset_n $end
$var wire 1 . shift_en $end
$var wire 1 / data_in $end
$var reg 5 0 data_out [4:0] $end
$upscope $end
$upscope $end

$scope begin std $end
$upscope $end
$enddefinitions $end
#0
$dumpvars
1!
1"
0#
x$
bx 0
b101 +
bx *
x)
x(
x'
x&
x%
1,
1-
0.
x/
$end
#1
0!
0,
#2
1!
1,
0"
0-
b0 0
0)
0(
0'
0&
0%
#3
0!
0,
#4
1!
1,
1"
b0 *
0$
b1 *
0/
1-
#5
0!
0,
#6
1!
1,
1$
b10 *
1/
#7
0!
0,
#8
1!
1,
b11 *
#9
0!
0,
#10
1!
1,
b100 *
#11
0!
0,
#12
1!
1,
1#
b0 *
b1 *
1.
#13
0!
0,
#14
1!
1,
0#
b10 *
0.
b10000 0
1%
#15
0!
0,
#16
1!
1,
b11 *
#17
0!
0,
#18
1!
1,
0$
b100 *
0/
#19
0!
0,
#20
1!
1,
1$
1#
b0 *
b1 *
1/
1.
#21
0!
0,
#22
1!
1,
0#
b10 *
0.
b11000 0
1&
#23
0!
0,
#24
1!
1,
0$
b11 *
0/
#25
0!
0,
#26
1!
1,
1$
b100 *
1/
#27
0!
0,
#28
1!
1,
1#
b0 *
b1 *
1.
#29
0!
0,
#30
1!
1,
0$
0#
b10 *
0/
0.
b11100 0
1'
#31
0!
0,
#32
1!
1,
1$
b11 *
1/
#33
0!
0,
#34
1!
1,
0$
b100 *
0/
#35
0!
0,
#36
1!
1,
1$
1#
b0 *
b1 *
1/
1.
#37
0!
0,
#38
1!
1,
0$
0#
b10 *
0/
0.
b11110 0
1(
#39
0!
0,
#40
1!
1,
1$
b11 *
1/
#41
0!
0,
#42
1!
1,
b100 *
#43
0!
0,
#44
1!
1,
0$
1#
b0 *
b1 *
0/
1.
#45
0!
0,
#46
1!
1,
1$
0#
b10 *
1/
0.
b1111 0
1)
0%
#47
0!
0,
#48
1!
1,
0$
b11 *
0/
#49
0!
0,
#50
1!
1,
b100 *
#51
0!
0,
#52
1!
1,
1#
b0 *
b1 *
1.
#53
0!
0,
#54
1!
1,
1$
0#
b10 *
1/
0.
b111 0
0&
#55
0!
0,
#56
1!
1,
0$
b11 *
0/
#57
0!
0,
#58
1!
1,
1$
b100 *
1/
#59
0!
0,
#60
1!
1,
1#
b0 *
b1 *
1.
#61
0!
0,
#62
1!
1,
0#
b10 *
0.
b10011 0
0'
1%
#63
0!
0,
#64
1!
1,
b11 *
#65
0!
0,
#66
1!
1,
0$
b100 *
0/
#67
0!
0,
#68
1!
1,
1#
b0 *
b1 *
1.
#69
0!
0,
#70
1!
1,
0#
b10 *
0.
b1001 0
0(
1&
0%
#71
0!
0,
#72
1!
1,
b11 *
#73
0!
0,
#74
1!
1,
1$
b100 *
1/
#75
0!
0,
#76
1!
1,
0$
1#
b0 *
b1 *
0/
1.
#77
0!
0,
#78
1!
1,
1$
0#
b10 *
1/
0.
b100 0
0)
1'
0&
#79
0!
0,
#80
1!
1,
b11 *
#81
0!
0,
#82
1!
1,
b100 *
#83
0!
0,
#84
1!
1,
1#
b0 *
b1 *
1.
#85
0!
0,
#86
1!
1,
0#
b10 *
0.
b10010 0
1(
0'
1%
#87
0!
0,
#88
1!
1,
0$
b11 *
0/
#89
0!
0,
#90
1!
1,
b100 *
#91
0!
0,
#92
1!
1,
1$
1#
b0 *
b1 *
1/
1.
#93
0!
0,
#94
1!
1,
0#
b10 *
0.
b11001 0
1)
0(
1&
#95
0!
0,
#96
1!
1,
b11 *
#97
0!
0,
#98
1!
1,
0$
b100 *
0/
#99
0!
0,
#100
1!
1,
1#
b0 *
b1 *
1.
#101
0!
0,
#102
1!
1,
0#
b10 *
0.
b1100 0
0)
1'
0%
#103
0!
0,
#104
1!
1,
b11 *
#105
0!
0,
#106
1!
1,
b100 *
#107
0!
0,
#108
1!
1,
1$
1#
b0 *
b1 *
1/
1.
#109
0!
0,
#110
1!
1,
0$
0#
b10 *
0/
0.
b10110 0
1(
0&
1%
#111
0!
0,
#112
1!
1,
b11 *
#113
0!
0,
#114
1!
1,
1$
b100 *
1/
#115
0!
0,
#116
1!
1,
1#
b0 *
b1 *
1.
#117
0!
0,
#118
1!
1,
0$
0#
b10 *
0/
0.
b11011 0
1)
0'
1&
#119
0!
0,
#120
1!
1,
b11 *
#121
0!
0,
#122
1!
1,
b100 *
#123
0!
0,
#124
1!
1,
1#
b0 *
b1 *
1.
#125
0!
0,
#126
1!
1,
0#
b10 *
0.
b1101 0
0(
1'
0%
#127
0!
0,
#128
1!
1,
1$
b11 *
1/
#129
0!
0,
#130
1!
1,
b100 *
#131
0!
0,
#132
1!
1,
1#
b0 *
b1 *
1.
#133
0!
0,
#134
1!
1,
0#
b10 *
0.
b10110 0
0)
1(
0&
1%
#135
0!
0,
#136
1!
1,
b11 *
#137
0!
0,
#138
1!
1,
0$
b100 *
0/
#139
0!
0,
#140
1!
1,
1#
b0 *
b1 *
1.
#141
0!
0,
#142
1!
1,
1$
0#
b10 *
1/
0.
b1011 0
1)
0'
1&
0%
#143
0!
0,
#144
1!
1,
b11 *
#145
0!
0,
#146
1!
1,
b100 *
#147
0!
0,
#148
1!
1,
0$
1#
b0 *
b1 *
0/
1.
#149
0!
0,
#150
1!
1,
0#
b10 *
0.
b101 0
0(
1'
0&
#151
0!
0,
#152
1!
1,
1$
b11 *
1/
#153
0!
0,
#154
1!
1,
b100 *
#155
0!
0,
#156
1!
1,
0$
1#
b0 *
b1 *
0/
1.
#157
0!
0,
#158
1!
1,
1$
0#
b10 *
1/
0.
b10 0
0)
1(
0'
#159
0!
0,
#160
1!
1,
b11 *
#161
0!
0,
#162
1!
1,
0$
b100 *
0/
#163
0!
0,
#164
1!
1,
1$
1#
b0 *
b1 *
1/
1.
#165
0!
0,
#166
1!
1,
0#
b10 *
0.
b10001 0
1)
0(
1%
#167
0!
0,
#168
1!
1,
b11 *
#169
0!
0,
#170
1!
1,
0$
b100 *
0/
#171
0!
0,
#172
1!
1,
1$
1#
b0 *
b1 *
1/
1.
#173
0!
0,
#174
1!
1,
0#
b10 *
0.
b11000 0
0)
1&
#175
0!
0,
#176
1!
1,
0$
b11 *
0/
#177
0!
0,
#178
1!
1,
b100 *
#179
0!
0,
#180
1!
1,
1#
b0 *
b1 *
1.
#181
0!
0,
#182
1!
1,
0#
b10 *
0.
b1100 0
1'
0%
#183
0!
0,
#184
1!
1,
1$
b11 *
1/
#185
0!
0,
#186
1!
1,
b100 *
#187
0!
0,
#188
1!
1,
0$
1#
b0 *
b1 *
0/
1.
#189
0!
0,
#190
1!
1,
0#
b10 *
0.
b110 0
1(
0&
#191
0!
0,
#192
1!
1,
1$
b11 *
1/
#193
0!
0,
#194
1!
1,
b100 *
#195
0!
0,
#196
1!
1,
1#
b0 *
b1 *
1.
#197
0!
0,
#198
1!
1,
0#
b10 *
0.
b10011 0
1)
0'
1%
#199
0!
0,
#200
1!
1,
b11 *
#201
0!
0,
#202
1!
1,
0$
b100 *
0/
